cordymotioncaller/CordyMotionCaller.py
cordymotioncaller/__init__.py
cordymotioncaller/bin/TcpClient
cordymotioncaller-0.2.0.dist-info/METADATA
cordymotioncaller-0.2.0.dist-info/WHEEL
cordymotioncaller-0.2.0.dist-info/entry_points.txt
cordymotioncaller-0.2.0.dist-info/top_level.txt
cordymotioncaller-0.2.0.dist-info/RECORD
