Metadata-Version: 2.1
Name: cordymotioncaller
Version: 0.2.0
Summary: Python wrapper for TcpClient
